gui_agents/__init__.py
gui_agents/utils.py
gui_agents/s1/__init__.py
gui_agents/s1/cli_app.py
gui_agents/s1/aci/ACI.py
gui_agents/s1/aci/LinuxOSACI.py
gui_agents/s1/aci/MacOSACI.py
gui_agents/s1/aci/WindowsOSACI.py
gui_agents/s1/aci/__init__.py
gui_agents/s1/core/AgentS.py
gui_agents/s1/core/BaseModule.py
gui_agents/s1/core/Knowledge.py
gui_agents/s1/core/Manager.py
gui_agents/s1/core/ProceduralMemory.py
gui_agents/s1/core/Worker.py
gui_agents/s1/core/__init__.py
gui_agents/s1/mllm/MultimodalAgent.py
gui_agents/s1/mllm/MultimodalEngine.py
gui_agents/s1/mllm/__init__.py
gui_agents/s1/utils/__init__.py
gui_agents/s1/utils/common_utils.py
gui_agents/s1/utils/ocr_server.py
gui_agents/s1/utils/query_perplexica.py
gui_agents/s2/__init__.py
gui_agents/s2/cli_app.py
gui_agents/s2/agents/__init__.py
gui_agents/s2/agents/agent_s.py
gui_agents/s2/agents/grounding.py
gui_agents/s2/agents/manager.py
gui_agents/s2/agents/worker.py
gui_agents/s2/core/__init__.py
gui_agents/s2/core/engine.py
gui_agents/s2/core/knowledge.py
gui_agents/s2/core/mllm.py
gui_agents/s2/core/module.py
gui_agents/s2/memory/__init__.py
gui_agents/s2/memory/procedural_memory.py
gui_agents/s2/utils/__init__.py
gui_agents/s2/utils/common_utils.py
gui_agents/s2/utils/query_perplexica.py
gui_agents/s2_5/__init__.py
gui_agents/s2_5/cli_app.py
gui_agents/s2_5/agents/__init__.py
gui_agents/s2_5/agents/agent_s.py
gui_agents/s2_5/agents/grounding.py
gui_agents/s2_5/agents/worker.py
gui_agents/s2_5/core/__init__.py
gui_agents/s2_5/core/engine.py
gui_agents/s2_5/core/mllm.py
gui_agents/s2_5/core/module.py
gui_agents/s2_5/memory/__init__.py
gui_agents/s2_5/memory/procedural_memory.py
gui_agents/s2_5/utils/__init__.py
gui_agents/s2_5/utils/common_utils.py
gui_agents/s3/__init__.py
gui_agents/s3/cli_app.py
gui_agents/s3/agents/__init__.py
gui_agents/s3/agents/agent_s.py
gui_agents/s3/agents/code_agent.py
gui_agents/s3/agents/grounding.py
gui_agents/s3/agents/worker.py
gui_agents/s3/bbon/__init__.py
gui_agents-0.3.2.dist-info/licenses/LICENSE
gui_agents-0.3.2.dist-info/METADATA
gui_agents-0.3.2.dist-info/WHEEL
gui_agents-0.3.2.dist-info/entry_points.txt
gui_agents-0.3.2.dist-info/top_level.txt
gui_agents-0.3.2.dist-info/RECORD
