Metadata-Version: 2.4
Name: gui-agents
Version: 0.3.2
Summary: A library for creating general purpose GUI agents using multimodal LLMs.
Author: Simular AI
Author-email: eric@simular.ai
Project-URL: Source, https://github.com/simular-ai/Agent-S
Project-URL: Bug Reports, https://github.com/simular-ai/Agent-S/issues
Keywords: ai,llm,gui,agent,multimodal
Classifier: Programming Language :: Python :: 3
Classifier: Programming Language :: Python :: 3.9
Classifier: License :: OSI Approved :: Apache Software License
Classifier: Operating System :: Microsoft :: Windows
Classifier: Operating System :: POSIX :: Linux
Classifier: Operating System :: MacOS :: MacOS X
Classifier: Topic :: Scientific/Engineering :: Artificial Intelligence
Requires-Python: >=3.9, <=3.12
License-File: LICENSE
Requires-Dist: numpy
Requires-Dist: backoff
Requires-Dist: pandas
Requires-Dist: openai
Requires-Dist: anthropic
Requires-Dist: fastapi
Requires-Dist: uvicorn
Requires-Dist: paddleocr
Requires-Dist: paddlepaddle
Requires-Dist: together
Requires-Dist: scikit-learn
Requires-Dist: websockets
Requires-Dist: tiktoken
Requires-Dist: selenium
Requires-Dist: pyobjc; platform_system == "Darwin"
Requires-Dist: pyautogui
Requires-Dist: toml
Requires-Dist: pytesseract
Requires-Dist: google-genai
Requires-Dist: pywinauto; platform_system == "Windows"
Requires-Dist: pywin32; platform_system == "Windows"
Provides-Extra: dev
Requires-Dist: black; extra == "dev"
Dynamic: author
Dynamic: author-email
Dynamic: classifier
Dynamic: description
Dynamic: description-content-type
Dynamic: keywords
Dynamic: license-file
Dynamic: project-url
Dynamic: provides-extra
Dynamic: requires-dist
Dynamic: requires-python
Dynamic: summary
